cisctl/__init__.py
cisctl/bash.py
cisctl/constants.py
cisctl/exception.py
cisctl/http.py
cisctl/logger.py
cisctl/render.py
cisctl/shell.py
cisctl/skopeo.py
cisctl/utils.py
cisctl/version.py
cisctl/api/__init__.py
cisctl/api/docker.py
cisctl/api/gcr.py
cisctl/api/quay.py
cisctl/template/README.md
cisctl/tests/__init__.py
cisctl/tests/unit/__init__.py
cisctl/tests/unit/test_http.py
cisctl/tests/unit/test_shell.py
cisctl/tests/unit/test_skopeo.py
cisctl/tests/unit/test_utils.py
cisctl/tests/unit/api/__init__.py
cisctl/tests/unit/api/test_docker.py
cisctl/tests/unit/api/test_gcr.py
python3_cisctl-1.1.0.dist-info/AUTHORS
python3_cisctl-1.1.0.dist-info/LICENSE
python3_cisctl-1.1.0.dist-info/METADATA
python3_cisctl-1.1.0.dist-info/WHEEL
python3_cisctl-1.1.0.dist-info/entry_points.txt
python3_cisctl-1.1.0.dist-info/pbr.json
python3_cisctl-1.1.0.dist-info/top_level.txt
python3_cisctl-1.1.0.dist-info/RECORD
