Metadata-Version: 2.1
Name: python3-cisctl
Version: 1.1.0
Summary: Container Images Sync Client
Home-page: https://www.xiexianbin.cn/
Author: xiexianbin
Author-email: me@xiexianbin.cn
Project-URL: Bug Tracker, https://github.com/x-actions/python3-cisctl/issues
Project-URL: Source Code, https://github.com/x-actions/python3-cisctl
Classifier: License :: OSI Approved :: Apache Software License
Classifier: Operating System :: POSIX :: Linux
Classifier: Programming Language :: Python :: 3
Classifier: Programming Language :: Python :: 3.6
Classifier: Programming Language :: Python :: 3.7
Classifier: Programming Language :: Python :: 3.8
Requires-Python: >=3.6
License-File: LICENSE
License-File: AUTHORS
Requires-Dist: pbr (>=5.5.0)
Requires-Dist: jinja2 (==3.0.3)
Requires-Dist: requests (==2.27.1)
Requires-Dist: setuptools (==65.1.1)
Provides-Extra: skopeo
Requires-Dist: skopeo (>=1.3.0) ; extra == 'skopeo'
